{
    "data": [
      {
        "id": "1",
        "name": "John Doe",
        "hours": [
          {
            "date": "2023-02-01",
            "start": "09:00",
            "end": "17:00"
          },
          {
            "date": "2023-02-02",
            "start": "08:30",
            "end": "16:30"
          }
        ]
      },
      {
        "id": "2",
        "name": "Alexa Doe",
        "hours": [
          {
            "date": "2023-02-01",
            "start": "08:00",
            "end": "16:00"
          },
          {
            "date": "2023-02-02",
            "start": "09:00",
            "end": "17:00"
          }
        ]
      },
      {
        "id": "3",
        "name": "Jane Doe",
        "hours": [
          {
            "date": "2023-02-01",
            "start": "08:00",
            "end": "16:00"
          },
          {
            "date": "2023-02-02",
            "start": "09:00",
            "end": "17:00"
          }
        ]
      },
      {
        "id": "4",
        "name": "Alex Doe",
        "hours": [
          {
            "date": "2023-02-01",
            "start": "08:00",
            "end": "16:00"
          },
          {
            "date": "2023-02-02",
            "start": "09:00",
            "end": "17:00"
          }
        ]
      },
      {
        "id": "5",
        "name": "Joe Doe",
        "hours": [
          {
            "date": "2023-02-01",
            "start": "08:00",
            "end": "16:00"
          },
          {
            "date": "2023-02-02",
            "start": "09:00",
            "end": "17:00"
          }
        ]
      }
    ]
  }